skbuild_conan/__init__.py
skbuild_conan/conan_helper.py
skbuild_conan/setup_wrapper.py
skbuild_conan-1.3.0.dist-info/LICENSE
skbuild_conan-1.3.0.dist-info/METADATA
skbuild_conan-1.3.0.dist-info/WHEEL
skbuild_conan-1.3.0.dist-info/top_level.txt
skbuild_conan-1.3.0.dist-info/RECORD
