Metadata-Version: 2.1
Name: skbuild_conan
Version: 1.3.0
Summary: An extension for scikit-build to add C++-dependencies as easily as Python dependencies via conan. 
Author-email: "TU Braunschweig, IBR, Algorithms Group (Dominik Krupke)" <krupke@ibr.cs.tu-bs.de>
License: MIT License
Project-URL: Homepage, https://github.com/d-krupke/skbuild-conan
Classifier: Programming Language :: Python :: 3
Classifier: License :: OSI Approved :: MIT License
Classifier: Development Status :: 3 - Alpha
Requires-Python: >=3.7
License-File: LICENSE
Requires-Dist: conan>=2.0.0
Requires-Dist: scikit-build>=0.17.3
Requires-Dist: setuptools
Requires-Dist: cmake>=3.23
Requires-Dist: ninja
